README.md
setup.py
pyminitouch/__init__.py
pyminitouch/actions.py
pyminitouch/config.py
pyminitouch/connection.py
pyminitouch/logger.py
pyminitouch/utils.py
pyminitouch.egg-info/PKG-INFO
pyminitouch.egg-info/SOURCES.txt
pyminitouch.egg-info/dependency_links.txt
pyminitouch.egg-info/requires.txt
pyminitouch.egg-info/top_level.txt