Metadata-Version: 1.0
Name: pyminitouch
Version: 0.3.0
Summary: python wrapper of minitouch, for better experience
Home-page: https://github.com/williamfzc/pyminitouch
Author: williamfzc
Author-email: fengzc@vip.qq.com
License: UNKNOWN
Platform: UNKNOWN
